gbp_archive-1.2.0.dist-info/METADATA
gbp_archive-1.2.0.dist-info/WHEEL
gbp_archive-1.2.0.dist-info/entry_points.txt
gbp_archive-1.2.0.dist-info/licenses/LICENSE
gbp_archive/__init__.py
gbp_archive/cli/__init__.py
gbp_archive/cli/dump.py
gbp_archive/cli/restore.py
gbp_archive/core.py
gbp_archive/metadata.py
gbp_archive/py.typed
gbp_archive/records.py
gbp_archive/storage.py
gbp_archive/types.py
gbp_archive/utils.py
gbp_archive-1.2.0.dist-info/RECORD
