Metadata-Version: 2.1
Name: gbp-archive
Version: 1.2.0
Summary: A Gentoo Build Publisher plugin to dump & restore builds
Author-Email: Albert Hopkins <marduk@letterboxes.org>
License: GPL3+
Project-URL: homepage, https://github.com/enku/gbp-archive
Project-URL: repository, https://github.com/enku/gbp-archive
Requires-Python: >=3.12
Requires-Dist: gbpcli>=2.5.0
Requires-Dist: gentoo-build-publisher>=3.0.1
Requires-Dist: dateparser>=1.2.1
Requires-Dist: orjson>=3.10.15
